setup.py
distributions04042020/Binomialdistribution.py
distributions04042020/Gaussiandistribution.py
distributions04042020/Generaldistribution.py
distributions04042020/__init__.py
distributions04042020.egg-info/PKG-INFO
distributions04042020.egg-info/SOURCES.txt
distributions04042020.egg-info/dependency_links.txt
distributions04042020.egg-info/not-zip-safe
distributions04042020.egg-info/top_level.txt